setup.py
dsnd_probability_rrld/Binomialdistribution.py
dsnd_probability_rrld/Gaussiandistribution.py
dsnd_probability_rrld/Generaldistribution.py
dsnd_probability_rrld/__init__.py
dsnd_probability_rrld.egg-info/PKG-INFO
dsnd_probability_rrld.egg-info/SOURCES.txt
dsnd_probability_rrld.egg-info/dependency_links.txt
dsnd_probability_rrld.egg-info/not-zip-safe
dsnd_probability_rrld.egg-info/top_level.txt