Metadata-Version: 1.0
Name: dsnd-probability-rrld
Version: 0.2
Summary: Gaussian and Binomial distributions
Home-page: UNKNOWN
Author: Rafael Roldao Udacity Student
Author-email: UNKNOWN
License: UNKNOWN
Platform: UNKNOWN
